DigiTwin_CO2_SampleProject/__init__.py
DigiTwin_CO2_SampleProject/main.py
DigiTwin_CO2_SampleProject/CO2_Prediction/__init__.py
DigiTwin_CO2_SampleProject/CO2_Prediction/config.py
DigiTwin_CO2_SampleProject/CO2_Prediction/database.py
DigiTwin_CO2_SampleProject/CO2_Prediction/logger.py
DigiTwin_CO2_SampleProject/CO2_Prediction/prediction.py
DigiTwin_CO2_SampleProject/CO2_Prediction/sensor.py
DigiTwin_CO2_SampleProject/CO2_Prediction/utils.py
DigiTwin_CO2_SampleProject/CO2_Prediction/window.py
DigiTwin_CO2_SampleProject/CO2_Prediction/zone.py
DigiTwin_CO2_SampleProject/MonitoringFaker/__init__.py
DigiTwin_CO2_SampleProject/MonitoringFaker/fake_measurement_data.py
DigiTwin_CO2_SampleProject/MonitoringFaker/utils.py
DigiTwin_CO2_SampleProject/SimultanCO2Prediction/__init__.py
DigiTwin_CO2_SampleProject/SimultanCO2Prediction/simultan_adaptions.py
DigiTwin_CO2_SampleProject/SimultanCO2Prediction/template.py
DigiTwin_CO2_SampleProject/SimultanCO2Prediction/resources/__init__.py
DigiTwin_CO2_SampleProject/SimultanCO2Prediction/resources/co2_prediction_template.yml
DigiTwin_CO2_SampleProject/SimultanCO2Prediction/resources/__pycache__/__init__.cpython-38.pyc
DigiTwin_CO2_SampleProject/SimultanCO2Prediction/resources/__pycache__/__init__.cpython-39.pyc
DigiTwin_CO2_SampleProject-2.dist-info/LICENSE.txt
DigiTwin_CO2_SampleProject-2.dist-info/METADATA
DigiTwin_CO2_SampleProject-2.dist-info/WHEEL
DigiTwin_CO2_SampleProject-2.dist-info/entry_points.txt
DigiTwin_CO2_SampleProject-2.dist-info/top_level.txt
DigiTwin_CO2_SampleProject-2.dist-info/RECORD
