Metadata-Version: 2.1
Name: DigiTwin-CO2-SampleProject
Version: 2
Summary: Project which shows the use of the SIMULTAN data model and Python for digital twins
Home-page: UNKNOWN
Author: Max Buehler
License: MIT
Keywords: python
Platform: UNKNOWN
Classifier: Development Status :: 4 - Beta
Classifier: Intended Audience :: Developers
Classifier: License :: OSI Approved :: MIT License
Classifier: Programming Language :: Python
Classifier: Programming Language :: Python :: 3
Classifier: Programming Language :: Python :: 3 :: Only
Classifier: Programming Language :: Python :: 3.8
Requires-Python: >=3.7
License-File: LICENSE.txt
Requires-Dist: numpy
Requires-Dist: pandas
Requires-Dist: sqlalchemy
Requires-Dist: PySimultan
Requires-Dist: matplotlib
